{
  "assetsByChunkName": {
    "vendors~app-account~app-confirmation~app-order": [
      "chunk.2e283384c4ca39cdde52.js",
      "chunk.2e283384c4ca39cdde52.js.map"
    ],
    "vendors~app-account~app-checkout": [
      "chunk.8ecdf69bd60612250774.js",
      "chunk.8ecdf69bd60612250774.js.map"
    ],
    "vendors~app-cart~app-checkout": [
      "chunk.b9dde3c1388fa3827411.js",
      "chunk.b9dde3c1388fa3827411.js.map"
    ],
    "admin": [
      "admin.0dd86987f37053c8ead6.js",
      "admin.0dd86987f37053c8ead6.js.map"
    ],
    "app-account": [
      "chunk.5756168f47597ee13ea9.js",
      "chunk.5756168f47597ee13ea9.js.map"
    ],
    "app-cart": [
      "chunk.be9ebc2cca85b000b58c.js",
      "chunk.be9ebc2cca85b000b58c.js.map"
    ],
    "app-confirmation": [
      "chunk.811cc893c50200c816af.js",
      "chunk.811cc893c50200c816af.js.map"
    ],
    "app-order": [
      "chunk.bf9d77bab11c2492a371.js",
      "chunk.bf9d77bab11c2492a371.js.map"
    ],
    "checkout": [
      "checkout.7e6ebbdfcbd290404790.js",
      "checkout.7e6ebbdfcbd290404790.js.map"
    ],
    "storefront": [
      "storefront.9f663dfcc05015cd0a29.css",
      "storefront.027aeaff8e41f10b6ae5.js",
      "storefront.9f663dfcc05015cd0a29.css.map",
      "storefront.027aeaff8e41f10b6ae5.js.map"
    ],
    "vendors~app-checkout": [
      "chunk.d7145d49d8ee63eb46b0.js",
      "chunk.d7145d49d8ee63eb46b0.js.map"
    ]
  }
}