{
  "assetsByChunkName": {
    "vendors~app-account~app-confirmation~app-order": [
      "chunk.cab3a947d01c013a3530.js",
      "chunk.cab3a947d01c013a3530.js.map"
    ],
    "vendors~app-account~app-checkout": [
      "chunk.8ecdf69bd60612250774.js",
      "chunk.8ecdf69bd60612250774.js.map"
    ],
    "vendors~app-cart~app-checkout": [
      "chunk.b9dde3c1388fa3827411.js",
      "chunk.b9dde3c1388fa3827411.js.map"
    ],
    "admin": [
      "admin.f8906758c72bece9fdc5.js",
      "admin.f8906758c72bece9fdc5.js.map"
    ],
    "app-account": [
      "chunk.5756168f47597ee13ea9.js",
      "chunk.5756168f47597ee13ea9.js.map"
    ],
    "app-cart": [
      "chunk.a708780b12c3bd4553f0.js",
      "chunk.a708780b12c3bd4553f0.js.map"
    ],
    "app-confirmation": [
      "chunk.811cc893c50200c816af.js",
      "chunk.811cc893c50200c816af.js.map"
    ],
    "app-order": [
      "chunk.bf9d77bab11c2492a371.js",
      "chunk.bf9d77bab11c2492a371.js.map"
    ],
    "checkout": [
      "checkout.965943b05e5eb0f0fee1.js",
      "checkout.965943b05e5eb0f0fee1.js.map"
    ],
    "storefront": [
      "storefront.9f663dfcc05015cd0a29.css",
      "storefront.4d40c9624675a3b415f3.js",
      "storefront.9f663dfcc05015cd0a29.css.map",
      "storefront.4d40c9624675a3b415f3.js.map"
    ],
    "vendors~app-checkout": [
      "chunk.e4ca0d62f4253ee09b09.js",
      "chunk.e4ca0d62f4253ee09b09.js.map"
    ]
  }
}